pd_shortcut.py
pd_shortcut-0.1.0.dist-info/WHEEL
pd_shortcut-0.1.0.dist-info/METADATA
pd_shortcut-0.1.0.dist-info/RECORD
