Metadata-Version: 2.4
Name: pd-shortcut
Version: 0.1.0
Summary: Shortcuts for working with pandas DataFrames.
Author-email: FEI YUAN <fei.yuan@bcm.edu>
Requires-Python: >=3.6
License-Expression: MIT
Requires-Dist: pandas
